AUTHORS.rst
CONTRIBUTING.rst
HISTORY.rst
LICENSE
MANIFEST.in
README.rst
pydgutils_bootstrap.py
requirements.txt
requirements_dev.txt
setup.cfg
setup.py
./src/rabird/__init__.py
./src/rabird.html.egg-info/PKG-INFO
./src/rabird.html.egg-info/SOURCES.txt
./src/rabird.html.egg-info/dependency_links.txt
./src/rabird.html.egg-info/not-zip-safe
./src/rabird.html.egg-info/requires.txt
./src/rabird.html.egg-info/top_level.txt
./src/rabird/html/__init__.py
./src/rabird/html/utils.py
./src/rabird/html/widgets/__init__.py
./src/rabird/html/widgets/table.py
./src/rabird/html/widgets/widget.py
docs/Makefile
docs/authors.rst
docs/conf.py
docs/contributing.rst
docs/history.rst
docs/index.rst
docs/installation.rst
docs/make.bat
docs/readme.rst
docs/usage.rst
src/__init__.py
src/rabird/__init__.py
src/rabird.html.egg-info/PKG-INFO
src/rabird.html.egg-info/SOURCES.txt
src/rabird.html.egg-info/dependency_links.txt
src/rabird.html.egg-info/not-zip-safe
src/rabird.html.egg-info/requires.txt
src/rabird.html.egg-info/top_level.txt
src/rabird/html/__init__.py
src/rabird/html/utils.py
src/rabird/html/widgets/__init__.py
src/rabird/html/widgets/table.py
src/rabird/html/widgets/widget.py
tests/__init__.py
tests/test_rabird_html.py